aws_cloudwatch_insights/__init__.py
aws_cloudwatch_insights/aws_cloudwatch_insights.py
aws_cloudwatch_insights/aws_cloudwatch_insights_tests.py
aws_cloudwatch_insights/cli.py
aws_cloudwatch_insights/cli_tests.py
aws_cloudwatch_insights-0.1.5.dist-info/LICENSE
aws_cloudwatch_insights-0.1.5.dist-info/METADATA
aws_cloudwatch_insights-0.1.5.dist-info/WHEEL
aws_cloudwatch_insights-0.1.5.dist-info/entry_points.txt
aws_cloudwatch_insights-0.1.5.dist-info/top_level.txt
aws_cloudwatch_insights-0.1.5.dist-info/RECORD
