Metadata-Version: 2.1
Name: aws-cloudwatch-insights
Version: 0.1.5
Summary: Library and cli for querying AWS Cloudwatch Insights
Home-page: https://github.com/valmikirao/aws_cloudwatch_insights
Author: Valmiki Rao
Author-email: valmikirao@gmail.com
License: MIT license
Keywords: aws,cloudwatch,insights
Platform: UNKNOWN
Classifier: Development Status :: 4 - Beta
Classifier: Intended Audience :: Developers
Classifier: License :: OSI Approved :: MIT License
Classifier: Natural Language :: English
Classifier: Programming Language :: Python :: 3
Classifier: Programming Language :: Python :: 3.7
Classifier: Programming Language :: Python :: 3.8
Classifier: Programming Language :: Python :: 3.9
Classifier: Programming Language :: Python :: 3.10
Classifier: Programming Language :: Python :: 3.11
Requires-Python: >=3.7
Requires-Dist: boto3 (<2.0.0,>=1.21.40)
Requires-Dist: botocore (<2.0.0,>=1.21.40)
Provides-Extra: cli
Requires-Dist: Click (<8.0.0,>=7.0.0) ; extra == 'cli'
Requires-Dist: timedeltafmt (<1.0.0,>=0.1.1) ; extra == 'cli'
Requires-Dist: PyYAML (<7.0.0,>=6.0.0) ; extra == 'cli'
Provides-Extra: lint
Requires-Dist: flake8 (<6.0.0,>=5.0.4) ; extra == 'lint'
Provides-Extra: test
Requires-Dist: pytest (<8.0.0,>=7.0.0) ; extra == 'test'
Requires-Dist: freezegun (<2.0.0,>=1.2.2) ; extra == 'test'
Requires-Dist: mypy (<2.0.0,>=1.0.1) ; extra == 'test'
Provides-Extra: types
Requires-Dist: boto3-stubs (<2.0.0,>=1.26.80) ; extra == 'types'
Requires-Dist: botocore-stubs (<2.0.0,>=1.29.80) ; extra == 'types'
Requires-Dist: mypy-boto3-logs (<2.0.0,>=1.26.53) ; extra == 'types'
Requires-Dist: types-PyYAML (<7.0.0,>=6.0.12.8) ; extra == 'types'
Requires-Dist: types-Pygments (<3.0.0,>=2.14.0.5) ; extra == 'types'
Requires-Dist: types-click (<8.0.0,>=7.1.8) ; extra == 'types'
Requires-Dist: types-colorama (<1.0.0,>=0.4.15.8) ; extra == 'types'
Requires-Dist: types-docutils (<1.0.0,>=0.19.1.6) ; extra == 'types'
Requires-Dist: types-python-dateutil (<3.0.0,>=2.8.19.9) ; extra == 'types'
Requires-Dist: types-setuptools (<68.0.0,>=67.4.0.3) ; extra == 'types'
